omnetpypy/__init__.py
omnetpypy/parser.py
omnetpypy/sim_log.py
omnetpypy/simulation.py
omnetpypy/utilities.py
omnetpypy/backends/__init__.py
omnetpypy/backends/connector.py
omnetpypy/backends/simpy_connector.py
omnetpypy/data/seeds.csv
omnetpypy/examples/__init__.py
omnetpypy/examples/ping_pong/__init__.py
omnetpypy/examples/ping_pong/main.py
omnetpypy/examples/ping_pong/ping_pong_simple.py
omnetpypy/examples/qnum_congestion_ctrl_aqm_bidir/__init__.py
omnetpypy/examples/qnum_congestion_ctrl_aqm_bidir/aqm_controller.py
omnetpypy/examples/qnum_congestion_ctrl_aqm_bidir/boxplots.py
omnetpypy/examples/qnum_congestion_ctrl_aqm_bidir/congestion_controller.py
omnetpypy/examples/qnum_congestion_ctrl_aqm_bidir/link_controller.py
omnetpypy/examples/qnum_congestion_ctrl_aqm_bidir/main.py
omnetpypy/examples/qnum_congestion_ctrl_aqm_bidir/messages.py
omnetpypy/examples/qnum_congestion_ctrl_aqm_bidir/plot_fidelity.py
omnetpypy/examples/qnum_congestion_ctrl_aqm_bidir/plot_fidelity_dynamic.py
omnetpypy/examples/qnum_congestion_ctrl_aqm_bidir/plot_latency_dynamic.py
omnetpypy/examples/qnum_congestion_ctrl_aqm_bidir/plot_latency_throughput.py
omnetpypy/examples/qnum_congestion_ctrl_aqm_bidir/plot_queue_size.py
omnetpypy/examples/qnum_congestion_ctrl_aqm_bidir/plot_queue_size_dynamic.py
omnetpypy/examples/qnum_congestion_ctrl_aqm_bidir/plot_rendezvous.py
omnetpypy/examples/qnum_congestion_ctrl_aqm_bidir/print_plot.py
omnetpypy/examples/qnum_congestion_ctrl_aqm_bidir/quantum_node.py
omnetpypy/examples/qnum_congestion_ctrl_aqm_bidir/queues.py
omnetpypy/examples/qnum_congestion_ctrl_aqm_bidir/utility.py
omnetpypy/front_end/__init__.py
omnetpypy/front_end/channel.py
omnetpypy/front_end/compound_module.py
omnetpypy/front_end/message.py
omnetpypy/front_end/port.py
omnetpypy/front_end/sim_entity.py
omnetpypy/front_end/simple_module.py
omnetpypy-0.1.4.dist-info/LICENSE
omnetpypy-0.1.4.dist-info/METADATA
omnetpypy-0.1.4.dist-info/WHEEL
omnetpypy-0.1.4.dist-info/top_level.txt
omnetpypy-0.1.4.dist-info/RECORD
